url_filter/__init__.py
url_filter/backends/__init__.py
url_filter/backends/base.py
url_filter/backends/django.py
url_filter/backends/plain.py
url_filter/backends/sqlalchemy.py
url_filter/constants.py
url_filter/exceptions.py
url_filter/fields.py
url_filter/filters.py
url_filter/filtersets/__init__.py
url_filter/filtersets/base.py
url_filter/filtersets/django.py
url_filter/filtersets/plain.py
url_filter/filtersets/sqlalchemy.py
url_filter/integrations/__init__.py
url_filter/integrations/drf.py
url_filter/integrations/drf_coreapi.py
url_filter/utils.py
url_filter/validators.py
dj_url_filter-0.4.4.dist-info/WHEEL
dj_url_filter-0.4.4.dist-info/LICENSE.rst
dj_url_filter-0.4.4.dist-info/METADATA
dj_url_filter-0.4.4.dist-info/RECORD
