Metadata-Version: 2.1
Name: dj-url-filter
Version: 0.4.4
Summary: Django URL Filter provides a safe way to filter data via human-friendly URLs.
License: MIT
Keywords: django,url-filter,drf
Author: Hat Dao
Author-email: enjoy3013@gmail.com
Requires-Python: >=3.9,<4.0
Classifier: Development Status :: 2 - Pre-Alpha
Classifier: Framework :: Django
Classifier: License :: OSI Approved :: MIT License
Classifier: Programming Language :: Python :: 3
Classifier: Programming Language :: Python :: 3.9
Classifier: Programming Language :: Python :: 3.10
Classifier: Programming Language :: Python :: 3.11
Classifier: Programming Language :: Python :: 3
Requires-Dist: cached-property (>=1.5.2,<2.0.0)
Requires-Dist: django (>=3.2.4)
